githubfork/githubfork.py
devatestPyGithubFork-0.0.2.dist-info/METADATA
devatestPyGithubFork-0.0.2.dist-info/WHEEL
devatestPyGithubFork-0.0.2.dist-info/top_level.txt
devatestPyGithubFork-0.0.2.dist-info/RECORD
