Metadata-Version: 2.1
Name: devatestPyGithubFork
Version: 0.0.2
Summary: Code wraps PyGithub to simplify workflows dealing with forks
Home-page: https://github.com/devakodali/PyGithubFork
Author: hassenius
Author-email: UNKNOWN
License: UNKNOWN
Platform: UNKNOWN
